classification_analysis/classification_analysis.py
classification_analysis-0.0.4.dist-info/LICENSE
classification_analysis-0.0.4.dist-info/METADATA
classification_analysis-0.0.4.dist-info/WHEEL
classification_analysis-0.0.4.dist-info/top_level.txt
classification_analysis-0.0.4.dist-info/RECORD
