Metadata-Version: 2.1
Name: classification-analysis
Version: 0.0.4
Summary: This library is to monitor your model during the training process and track the metrics to find the best model
Home-page: https://github.com/Samer92/classification_analysis
Author: sammer sallam
Author-email: samersallam92@gmail.com
License: UNKNOWN
Platform: UNKNOWN
Classifier: Programming Language :: Python :: 3
Classifier: License :: OSI Approved :: MIT License
Classifier: Operating System :: OS Independent
Requires-Python: >=3.6
Requires-Dist: cycler (==0.10.0)
Requires-Dist: imbalanced-learn (==0.7.0)
Requires-Dist: imblearn (==0.0)
Requires-Dist: joblib (==0.17.0)
Requires-Dist: kiwisolver (==1.2.0)
Requires-Dist: matplotlib (==3.2.2)
Requires-Dist: numpy (==1.19.0)
Requires-Dist: pandas (==1.0.5)
Requires-Dist: Pillow (==7.1.2)
Requires-Dist: pyparsing (==2.4.7)
Requires-Dist: python-dateutil (==2.8.1)
Requires-Dist: pytz (==2020.1)
Requires-Dist: scikit-learn (==0.23.2)
Requires-Dist: scipy (==1.5.0)
Requires-Dist: six (==1.15.0)
Requires-Dist: threadpoolctl (==2.1.0)
